README.txt
expecter.py
setup.py
expecter.egg-info/PKG-INFO
expecter.egg-info/SOURCES.txt
expecter.egg-info/dependency_links.txt
expecter.egg-info/top_level.txt