Metadata-Version: 1.0
Name: expecter
Version: 0.2.2
Summary: Expecter Gadget, a better expectation (assertion) library
Home-page: https://github.com/garybernhardt/expecter
Author: Gary Bernhardt
Author-email: gary.bernhardt@gmail.com
License: BSD
Platform: UNKNOWN
Classifier: Development Status :: 3 - Alpha
Classifier: Topic :: Software Development :: Testing
Classifier: Intended Audience :: Developers
